{"gsisId": "00-0040129", "displayName": "Emeka Egbuka", "position": "WR", "tier": "star", "rating": 52, "seasonsCovered": [2015, 2025], "totalPlaysSampled": 128, "buckets": {"receiver": [{"bucketKey": "1_long_own_territory", "sampleSize": 22, "outcomes": [{"yards": 0, "isTouchdown": false, "isTurnover": false, "isSack": false, "isComplete": false, "isFirstDown": false, "depthTier": "medium", "isScramble": false}, {"yards": 9, "isTouchdown": false, "isTurnover": false, "isSack": false, "isComplete": true, "isFirstDown": false, "depthTier": "short", "isScramble": false}, {"yards": 3, "isTouchdown": false, "isTurnover": false, "isSack": false, "isComplete": true, "isFirstDown": false, "depthTier": "short", "isScramble": false}, {"yards": 77, "isTouchdown": true, "isTurnover": false, "isSack": false, "isComplete": true, "isFirstDown": true, "depthTier": "deep", "isScramble": false}, {"yards": 19, "isTouchdown": false, "isTurnover": false, "isSack": false, "isComplete": true, "isFirstDown": true, "depthTier": "medium", "isScramble": false}, {"yards": 25, "isTouchdown": false, "isTurnover": false, "isSack": false, "isComplete": true, "isFirstDown": true, "depthTier": "medium", "isScramble": false}, {"yards": 7, "isTouchdown": false, "isTurnover": false, "isSack": false, "isComplete": true, "isFirstDown": false, "depthTier": "short", "isScramble": false}, {"yards": 0, "isTouchdown": false, "isTurnover": false, "isSack": false, "isComplete": false, "isFirstDown": false, "depthTier": "deep", "isScramble": false}, {"yards": 30, "isTouchdown": false, "isTurnover": false, "isSack": false, "isComplete": true, "isFirstDown": true, "depthTier": "medium", "isScramble": false}, {"yards": 7, "isTouchdown": false, "isTurnover": false, "isSack": false, "isComplete": true, "isFirstDown": false, "depthTier": "short", "isScramble": false}, {"yards": 0, "isTouchdown": false, "isTurnover": false, "isSack": false, "isComplete": false, "isFirstDown": false, "depthTier": "medium", "isScramble": false}, {"yards": 8, "isTouchdown": false, "isTurnover": false, "isSack": false, "isComplete": true, "isFirstDown": false, "depthTier": "short", "isScramble": false}, {"yards": 0, "isTouchdown": false, "isTurnover": false, "isSack": false, "isComplete": false, "isFirstDown": false, "depthTier": "medium", "isScramble": false}, {"yards": 0, "isTouchdown": false, "isTurnover": false, "isSack": false, "isComplete": false, "isFirstDown": false, "depthTier": "medium", "isScramble": false}, {"yards": 6, "isTouchdown": false, "isTurnover": false, "isSack": false, "isComplete": true, "isFirstDown": false, "depthTier": "short", "isScramble": false}, {"yards": 0, "isTouchdown": false, "isTurnover": false, "isSack": false, "isComplete": false, "isFirstDown": false, "depthTier": "medium", "isScramble": false}, {"yards": 12, "isTouchdown": false, "isTurnover": false, "isSack": false, "isComplete": true, "isFirstDown": true, "depthTier": "short", "isScramble": false}, {"yards": 20, "isTouchdown": false, "isTurnover": false, "isSack": false, "isComplete": true, "isFirstDown": true, "depthTier": "medium", "isScramble": false}, {"yards": 7, "isTouchdown": false, "isTurnover": false, "isSack": false, "isComplete": true, "isFirstDown": false, "depthTier": "short", "isScramble": false}, {"yards": 6, "isTouchdown": false, "isTurnover": false, "isSack": false, "isComplete": true, "isFirstDown": false, "depthTier": "short", "isScramble": false}, {"yards": 7, "isTouchdown": false, "isTurnover": false, "isSack": false, "isComplete": true, "isFirstDown": false, "depthTier": "short", "isScramble": false}, {"yards": 8, "isTouchdown": false, "isTurnover": false, "isSack": false, "isComplete": true, "isFirstDown": false, "depthTier": "short", "isScramble": false}]}, {"bucketKey": "3_short_red_zone", "sampleSize": 2, "outcomes": [{"yards": 30, "isTouchdown": true, "isTurnover": false, "isSack": false, "isComplete": true, "isFirstDown": true, "depthTier": "deep", "isScramble": false}, {"yards": 0, "isTouchdown": false, "isTurnover": false, "isSack": false, "isComplete": false, "isFirstDown": false, "depthTier": "short", "isScramble": false}]}, {"bucketKey": "1_long_midfield", "sampleSize": 13, "outcomes": [{"yards": 0, "isTouchdown": false, "isTurnover": false, "isSack": false, "isComplete": false, "isFirstDown": false, "depthTier": "short", "isScramble": false}, {"yards": 0, "isTouchdown": false, "isTurnover": false, "isSack": false, "isComplete": false, "isFirstDown": false, "depthTier": "deep", "isScramble": false}, {"yards": 8, "isTouchdown": false, "isTurnover": false, "isSack": false, "isComplete": true, "isFirstDown": false, "depthTier": "short", "isScramble": false}, {"yards": 0, "isTouchdown": false, "isTurnover": false, "isSack": false, "isComplete": false, "isFirstDown": false, "depthTier": "deep", "isScramble": false}, {"yards": 24, "isTouchdown": false, "isTurnover": false, "isSack": false, "isComplete": true, "isFirstDown": true, "depthTier": "deep", "isScramble": false}, {"yards": 31, "isTouchdown": false, "isTurnover": false, "isSack": false, "isComplete": true, "isFirstDown": true, "depthTier": "deep", "isScramble": false}, {"yards": 21, "isTouchdown": false, "isTurnover": false, "isSack": false, "isComplete": true, "isFirstDown": true, "depthTier": "medium", "isScramble": false}, {"yards": 0, "isTouchdown": false, "isTurnover": false, "isSack": false, "isComplete": false, "isFirstDown": false, "depthTier": "short", "isScramble": false}, {"yards": 8, "isTouchdown": false, "isTurnover": false, "isSack": false, "isComplete": true, "isFirstDown": false, "depthTier": "short", "isScramble": false}, {"yards": 0, "isTouchdown": false, "isTurnover": false, "isSack": false, "isComplete": false, "isFirstDown": false, "depthTier": "deep", "isScramble": false}, {"yards": -3, "isTouchdown": false, "isTurnover": false, "isSack": false, "isComplete": true, "isFirstDown": false, "depthTier": "short", "isScramble": false}, {"yards": 9, "isTouchdown": false, "isTurnover": false, "isSack": false, "isComplete": true, "isFirstDown": false, "depthTier": "short", "isScramble": false}, {"yards": 0, "isTouchdown": false, "isTurnover": false, "isSack": false, "isComplete": false, "isFirstDown": false, "depthTier": "short", "isScramble": false}]}, {"bucketKey": "1_long_red_zone", "sampleSize": 10, "outcomes": [{"yards": 25, "isTouchdown": true, "isTurnover": false, "isSack": false, "isComplete": true, "isFirstDown": true, "depthTier": "deep", "isScramble": false}, {"yards": 0, "isTouchdown": false, "isTurnover": false, "isSack": false, "isComplete": false, "isFirstDown": false, "depthTier": "deep", "isScramble": false}, {"yards": 9, "isTouchdown": false, "isTurnover": false, "isSack": false, "isComplete": true, "isFirstDown": false, "depthTier": "short", "isScramble": false}, {"yards": 0, "isTouchdown": false, "isTurnover": false, "isSack": false, "isComplete": false, "isFirstDown": false, "depthTier": "deep", "isScramble": false}, {"yards": 21, "isTouchdown": true, "isTurnover": false, "isSack": false, "isComplete": true, "isFirstDown": true, "depthTier": "medium", "isScramble": false}, {"yards": 0, "isTouchdown": false, "isTurnover": false, "isSack": false, "isComplete": false, "isFirstDown": false, "depthTier": "medium", "isScramble": false}, {"yards": 10, "isTouchdown": false, "isTurnover": false, "isSack": false, "isComplete": true, "isFirstDown": true, "depthTier": "short", "isScramble": false}, {"yards": 0, "isTouchdown": false, "isTurnover": false, "isSack": false, "isComplete": false, "isFirstDown": false, "depthTier": "deep", "isScramble": false}, {"yards": 0, "isTouchdown": false, "isTurnover": false, "isSack": false, "isComplete": false, "isFirstDown": false, "depthTier": "deep", "isScramble": false}, {"yards": 0, "isTouchdown": false, "isTurnover": true, "isSack": false, "isComplete": false, "isFirstDown": false, "depthTier": "deep", "isScramble": false}]}, {"bucketKey": "3_short_own_territory", "sampleSize": 4, "outcomes": [{"yards": 3, "isTouchdown": false, "isTurnover": false, "isSack": false, "isComplete": true, "isFirstDown": true, "depthTier": "short", "isScramble": false}, {"yards": 1, "isTouchdown": false, "isTurnover": false, "isSack": false, "isComplete": true, "isFirstDown": false, "depthTier": "short", "isScramble": false}, {"yards": 0, "isTouchdown": false, "isTurnover": false, "isSack": false, "isComplete": false, "isFirstDown": false, "depthTier": "deep", "isScramble": false}, {"yards": 0, "isTouchdown": false, "isTurnover": false, "isSack": false, "isComplete": false, "isFirstDown": false, "depthTier": "short", "isScramble": false}]}, {"bucketKey": "2_medium_red_zone", "sampleSize": 3, "outcomes": [{"yards": 4, "isTouchdown": false, "isTurnover": false, "isSack": false, "isComplete": true, "isFirstDown": true, "depthTier": "short", "isScramble": false}, {"yards": -3, "isTouchdown": false, "isTurnover": false, "isSack": false, "isComplete": true, "isFirstDown": false, "depthTier": "short", "isScramble": false}, {"yards": 2, "isTouchdown": false, "isTurnover": false, "isSack": false, "isComplete": true, "isFirstDown": false, "depthTier": "short", "isScramble": false}]}, {"bucketKey": "3_medium_red_zone", "sampleSize": 1, "outcomes": [{"yards": 15, "isTouchdown": true, "isTurnover": false, "isSack": false, "isComplete": true, "isFirstDown": true, "depthTier": "short", "isScramble": false}]}, {"bucketKey": "3_long_own_territory", "sampleSize": 4, "outcomes": [{"yards": 7, "isTouchdown": false, "isTurnover": false, "isSack": false, "isComplete": true, "isFirstDown": false, "depthTier": "short", "isScramble": false}, {"yards": 0, "isTouchdown": false, "isTurnover": false, "isSack": false, "isComplete": false, "isFirstDown": false, "depthTier": "deep", "isScramble": false}, {"yards": 0, "isTouchdown": false, "isTurnover": false, "isSack": false, "isComplete": false, "isFirstDown": false, "depthTier": "short", "isScramble": false}, {"yards": 23, "isTouchdown": false, "isTurnover": false, "isSack": false, "isComplete": true, "isFirstDown": true, "depthTier": "medium", "isScramble": false}]}, {"bucketKey": "2_long_red_zone", "sampleSize": 7, "outcomes": [{"yards": 0, "isTouchdown": false, "isTurnover": false, "isSack": false, "isComplete": false, "isFirstDown": false, "depthTier": "medium", "isScramble": false}, {"yards": 5, "isTouchdown": false, "isTurnover": false, "isSack": false, "isComplete": true, "isFirstDown": false, "depthTier": "short", "isScramble": false}, {"yards": 0, "isTouchdown": false, "isTurnover": false, "isSack": false, "isComplete": false, "isFirstDown": false, "depthTier": "deep", "isScramble": false}, {"yards": 0, "isTouchdown": false, "isTurnover": false, "isSack": false, "isComplete": false, "isFirstDown": false, "depthTier": "medium", "isScramble": false}, {"yards": 0, "isTouchdown": false, "isTurnover": false, "isSack": false, "isComplete": false, "isFirstDown": false, "depthTier": "short", "isScramble": false}, {"yards": 0, "isTouchdown": false, "isTurnover": false, "isSack": false, "isComplete": false, "isFirstDown": false, "depthTier": "short", "isScramble": false}, {"yards": 0, "isTouchdown": false, "isTurnover": false, "isSack": false, "isComplete": false, "isFirstDown": false, "depthTier": "deep", "isScramble": false}]}, {"bucketKey": "2_long_own_territory", "sampleSize": 14, "outcomes": [{"yards": 30, "isTouchdown": false, "isTurnover": false, "isSack": false, "isComplete": true, "isFirstDown": true, "depthTier": "deep", "isScramble": false}, {"yards": 28, "isTouchdown": false, "isTurnover": false, "isSack": false, "isComplete": true, "isFirstDown": true, "depthTier": "deep", "isScramble": false}, {"yards": 18, "isTouchdown": false, "isTurnover": false, "isSack": false, "isComplete": true, "isFirstDown": true, "depthTier": "medium", "isScramble": false}, {"yards": 17, "isTouchdown": false, "isTurnover": false, "isSack": false, "isComplete": true, "isFirstDown": true, "depthTier": "medium", "isScramble": false}, {"yards": 4, "isTouchdown": false, "isTurnover": false, "isSack": false, "isComplete": true, "isFirstDown": false, "depthTier": "short", "isScramble": false}, {"yards": 6, "isTouchdown": false, "isTurnover": false, "isSack": false, "isComplete": true, "isFirstDown": false, "depthTier": "short", "isScramble": false}, {"yards": 8, "isTouchdown": false, "isTurnover": false, "isSack": false, "isComplete": true, "isFirstDown": false, "depthTier": "short", "isScramble": false}, {"yards": 0, "isTouchdown": false, "isTurnover": false, "isSack": false, "isComplete": false, "isFirstDown": false, "depthTier": "short", "isScramble": false}, {"yards": 0, "isTouchdown": false, "isTurnover": false, "isSack": false, "isComplete": false, "isFirstDown": false, "depthTier": "medium", "isScramble": false}, {"yards": 9, "isTouchdown": false, "isTurnover": false, "isSack": false, "isComplete": true, "isFirstDown": false, "depthTier": "short", "isScramble": false}, {"yards": 0, "isTouchdown": false, "isTurnover": false, "isSack": false, "isComplete": false, "isFirstDown": false, "depthTier": "medium", "isScramble": false}, {"yards": 0, "isTouchdown": false, "isTurnover": false, "isSack": false, "isComplete": false, "isFirstDown": false, "depthTier": "deep", "isScramble": false}, {"yards": 0, "isTouchdown": false, "isTurnover": false, "isSack": false, "isComplete": false, "isFirstDown": false, "depthTier": "medium", "isScramble": false}, {"yards": 40, "isTouchdown": false, "isTurnover": false, "isSack": false, "isComplete": true, "isFirstDown": true, "depthTier": "deep", "isScramble": false}]}, {"bucketKey": "3_short_midfield", "sampleSize": 2, "outcomes": [{"yards": 11, "isTouchdown": false, "isTurnover": false, "isSack": false, "isComplete": true, "isFirstDown": true, "depthTier": "short", "isScramble": false}, {"yards": 0, "isTouchdown": false, "isTurnover": false, "isSack": false, "isComplete": false, "isFirstDown": false, "depthTier": "short", "isScramble": false}]}, {"bucketKey": "3_long_red_zone", "sampleSize": 5, "outcomes": [{"yards": 11, "isTouchdown": false, "isTurnover": false, "isSack": false, "isComplete": true, "isFirstDown": true, "depthTier": "short", "isScramble": false}, {"yards": 20, "isTouchdown": true, "isTurnover": false, "isSack": false, "isComplete": true, "isFirstDown": true, "depthTier": "deep", "isScramble": false}, {"yards": 0, "isTouchdown": false, "isTurnover": false, "isSack": false, "isComplete": false, "isFirstDown": false, "depthTier": "short", "isScramble": false}, {"yards": 0, "isTouchdown": false, "isTurnover": false, "isSack": false, "isComplete": false, "isFirstDown": false, "depthTier": "medium", "isScramble": false}, {"yards": 0, "isTouchdown": false, "isTurnover": false, "isSack": false, "isComplete": false, "isFirstDown": false, "depthTier": "medium", "isScramble": false}]}, {"bucketKey": "3_medium_midfield", "sampleSize": 2, "outcomes": [{"yards": 0, "isTouchdown": false, "isTurnover": false, "isSack": false, "isComplete": false, "isFirstDown": false, "depthTier": "short", "isScramble": false}, {"yards": 0, "isTouchdown": false, "isTurnover": false, "isSack": false, "isComplete": false, "isFirstDown": false, "depthTier": "medium", "isScramble": false}]}, {"bucketKey": "2_short_own_territory", "sampleSize": 1, "outcomes": [{"yards": 0, "isTouchdown": false, "isTurnover": false, "isSack": false, "isComplete": false, "isFirstDown": false, "depthTier": "medium", "isScramble": false}]}, {"bucketKey": "2_medium_own_territory", "sampleSize": 8, "outcomes": [{"yards": 0, "isTouchdown": false, "isTurnover": false, "isSack": false, "isComplete": false, "isFirstDown": false, "depthTier": "medium", "isScramble": false}, {"yards": 0, "isTouchdown": false, "isTurnover": false, "isSack": false, "isComplete": false, "isFirstDown": false, "depthTier": "medium", "isScramble": false}, {"yards": 18, "isTouchdown": false, "isTurnover": false, "isSack": false, "isComplete": true, "isFirstDown": true, "depthTier": "medium", "isScramble": false}, {"yards": 24, "isTouchdown": false, "isTurnover": false, "isSack": false, "isComplete": true, "isFirstDown": true, "depthTier": "medium", "isScramble": false}, {"yards": 6, "isTouchdown": false, "isTurnover": false, "isSack": false, "isComplete": true, "isFirstDown": false, "depthTier": "short", "isScramble": false}, {"yards": 0, "isTouchdown": false, "isTurnover": false, "isSack": false, "isComplete": false, "isFirstDown": false, "depthTier": "medium", "isScramble": false}, {"yards": 3, "isTouchdown": false, "isTurnover": false, "isSack": false, "isComplete": true, "isFirstDown": false, "depthTier": "short", "isScramble": false}, {"yards": 0, "isTouchdown": false, "isTurnover": false, "isSack": false, "isComplete": false, "isFirstDown": false, "depthTier": "short", "isScramble": false}]}, {"bucketKey": "2_long_midfield", "sampleSize": 9, "outcomes": [{"yards": 9, "isTouchdown": false, "isTurnover": false, "isSack": false, "isComplete": true, "isFirstDown": true, "depthTier": "short", "isScramble": false}, {"yards": 0, "isTouchdown": false, "isTurnover": false, "isSack": false, "isComplete": false, "isFirstDown": false, "depthTier": "medium", "isScramble": false}, {"yards": 0, "isTouchdown": false, "isTurnover": false, "isSack": false, "isComplete": false, "isFirstDown": false, "depthTier": "medium", "isScramble": false}, {"yards": 4, "isTouchdown": false, "isTurnover": false, "isSack": false, "isComplete": true, "isFirstDown": false, "depthTier": "short", "isScramble": false}, {"yards": 0, "isTouchdown": false, "isTurnover": false, "isSack": false, "isComplete": false, "isFirstDown": false, "depthTier": "medium", "isScramble": false}, {"yards": 0, "isTouchdown": false, "isTurnover": false, "isSack": false, "isComplete": false, "isFirstDown": false, "depthTier": "medium", "isScramble": false}, {"yards": 11, "isTouchdown": false, "isTurnover": false, "isSack": false, "isComplete": true, "isFirstDown": true, "depthTier": "medium", "isScramble": false}, {"yards": 32, "isTouchdown": false, "isTurnover": false, "isSack": false, "isComplete": true, "isFirstDown": true, "depthTier": "medium", "isScramble": false}, {"yards": 8, "isTouchdown": false, "isTurnover": false, "isSack": false, "isComplete": true, "isFirstDown": false, "depthTier": "short", "isScramble": false}]}, {"bucketKey": "3_long_midfield", "sampleSize": 8, "outcomes": [{"yards": 57, "isTouchdown": false, "isTurnover": false, "isSack": false, "isComplete": true, "isFirstDown": true, "depthTier": "deep", "isScramble": false}, {"yards": 24, "isTouchdown": false, "isTurnover": false, "isSack": false, "isComplete": true, "isFirstDown": true, "depthTier": "medium", "isScramble": false}, {"yards": 7, "isTouchdown": false, "isTurnover": false, "isSack": false, "isComplete": true, "isFirstDown": false, "depthTier": "short", "isScramble": false}, {"yards": 0, "isTouchdown": false, "isTurnover": false, "isSack": false, "isComplete": false, "isFirstDown": false, "depthTier": "medium", "isScramble": false}, {"yards": 0, "isTouchdown": false, "isTurnover": false, "isSack": false, "isComplete": false, "isFirstDown": false, "depthTier": "medium", "isScramble": false}, {"yards": 0, "isTouchdown": false, "isTurnover": false, "isSack": false, "isComplete": false, "isFirstDown": false, "depthTier": "deep", "isScramble": false}, {"yards": 0, "isTouchdown": false, "isTurnover": false, "isSack": false, "isComplete": false, "isFirstDown": false, "depthTier": "medium", "isScramble": false}, {"yards": 23, "isTouchdown": false, "isTurnover": false, "isSack": false, "isComplete": true, "isFirstDown": true, "depthTier": "medium", "isScramble": false}]}, {"bucketKey": "3_medium_own_territory", "sampleSize": 4, "outcomes": [{"yards": 0, "isTouchdown": false, "isTurnover": false, "isSack": false, "isComplete": false, "isFirstDown": false, "depthTier": "medium", "isScramble": false}, {"yards": 0, "isTouchdown": false, "isTurnover": false, "isSack": false, "isComplete": false, "isFirstDown": false, "depthTier": "medium", "isScramble": false}, {"yards": 0, "isTouchdown": false, "isTurnover": true, "isSack": false, "isComplete": false, "isFirstDown": false, "depthTier": "short", "isScramble": false}, {"yards": 0, "isTouchdown": false, "isTurnover": true, "isSack": false, "isComplete": false, "isFirstDown": false, "depthTier": "medium", "isScramble": false}]}, {"bucketKey": "2_short_red_zone", "sampleSize": 1, "outcomes": [{"yards": 0, "isTouchdown": false, "isTurnover": false, "isSack": false, "isComplete": false, "isFirstDown": false, "depthTier": "deep", "isScramble": false}]}, {"bucketKey": "4_long_red_zone", "sampleSize": 1, "outcomes": [{"yards": 0, "isTouchdown": false, "isTurnover": false, "isSack": false, "isComplete": false, "isFirstDown": false, "depthTier": "medium", "isScramble": false}]}, {"bucketKey": "1_medium_own_territory", "sampleSize": 1, "outcomes": [{"yards": 0, "isTouchdown": false, "isTurnover": false, "isSack": false, "isComplete": false, "isFirstDown": false, "depthTier": "short", "isScramble": false}]}, {"bucketKey": "3_short_goal_line", "sampleSize": 1, "outcomes": [{"yards": 0, "isTouchdown": false, "isTurnover": false, "isSack": false, "isComplete": false, "isFirstDown": false, "depthTier": "short", "isScramble": false}]}, {"bucketKey": "2_medium_midfield", "sampleSize": 2, "outcomes": [{"yards": 0, "isTouchdown": false, "isTurnover": false, "isSack": false, "isComplete": false, "isFirstDown": false, "depthTier": "short", "isScramble": false}, {"yards": 9, "isTouchdown": false, "isTurnover": false, "isSack": false, "isComplete": true, "isFirstDown": true, "depthTier": "short", "isScramble": false}]}, {"bucketKey": "3_medium_goal_line", "sampleSize": 1, "outcomes": [{"yards": 0, "isTouchdown": false, "isTurnover": false, "isSack": false, "isComplete": false, "isFirstDown": false, "depthTier": "short", "isScramble": false}]}, {"bucketKey": "2_short_midfield", "sampleSize": 1, "outcomes": [{"yards": 0, "isTouchdown": false, "isTurnover": false, "isSack": false, "isComplete": false, "isFirstDown": false, "depthTier": "deep", "isScramble": false}]}]}, "aggregates": {"receiver": {"sampleSize": 128, "catchRate": 0.4921875, "yardsPerTarget": 7.34375, "receivingTdRate": 0.046875, "firstDownRate": 0.265625, "intRate": 0.0234375, "byDepth": {"short": {"sampleSize": 56, "catchRate": 0.6785714285714286, "yardsPerTarget": 4.464285714285714, "receivingTdRate": 0.017857142857142856, "firstDownRate": 0.16071428571428573, "intRate": 0.017857142857142856}, "medium": {"sampleSize": 44, "catchRate": 0.3409090909090909, "yardsPerTarget": 7.409090909090909, "receivingTdRate": 0.022727272727272728, "firstDownRate": 0.3409090909090909, "intRate": 0.022727272727272728}, "deep": {"sampleSize": 27, "catchRate": 0.37037037037037035, "yardsPerTarget": 13.407407407407407, "receivingTdRate": 0.14814814814814814, "firstDownRate": 0.37037037037037035, "intRate": 0.037037037037037035}}}}}